groqchat/README.md
groqchat/__init__.py
groqchat/config.py
groqchat/main.py
groqchat/requirements.txt
groqchat/audio/notification1_mild.mp3
groqchat/audio/notification2_mild.mp3
groqchat/temp/Readme.md
groqchat/utils/promptValidator.py
groqchat/utils/single_prompt.py
groqchat/utils/streaming_word_wrapper.py
groqchat/utils/terminal_mode_dialogs.py
groqchat/utils/tts_utils.py
groqchat-0.0.17.dist-info/METADATA
groqchat-0.0.17.dist-info/WHEEL
groqchat-0.0.17.dist-info/entry_points.txt
groqchat-0.0.17.dist-info/top_level.txt
groqchat-0.0.17.dist-info/RECORD
