Metadata-Version: 2.1
Name: groqchat
Version: 0.0.17
Summary: A terminal chatbot, powered by Groq Cloud API (Windows / macOS / Linux / Android / iOS)
Home-page: https://letmedoit.ai
Author: Eliran Wong
Author-email: support@letmedoit.ai
License: GNU General Public License (GPL)
Project-URL: Source, https://github.com/eliranwong/groqchat
Project-URL: Tracker, https://github.com/eliranwong/groqchat/issues
Project-URL: Documentation, https://github.com/eliranwong/groqchat/wiki
Project-URL: Funding, https://www.paypal.me/letmedoitai
Keywords: ai google gemini palm codey vertex api multimodal vision
Classifier: Development Status :: 5 - Production/Stable
Classifier: Intended Audience :: End Users/Desktop
Classifier: Topic :: Utilities
Classifier: License :: OSI Approved :: GNU General Public License v3 or later (GPLv3+)
Classifier: Programming Language :: Python :: 3.8
Classifier: Programming Language :: Python :: 3.9
Classifier: Programming Language :: Python :: 3.10
Classifier: Programming Language :: Python :: 3.11
Classifier: Programming Language :: Python :: 3.12
Requires-Python: >=3.8
Requires-Dist: prompt-toolkit
Requires-Dist: groq
Requires-Dist: soundfile ==0.12.1
Requires-Dist: sounddevice ==0.4.7
Requires-Dist: SpeechRecognition
Requires-Dist: psutil
Requires-Dist: numpy ==1.26.4
